gosuslugi_api/__init__.py
gosuslugi_api/clients.py
gosuslugi_api/consts.py
gosuslugi_api/exceptions.py
gosuslugi_api/utils.py
gosuslugi_api-0.7.0.dist-info/LICENCE.txt
gosuslugi_api-0.7.0.dist-info/METADATA
gosuslugi_api-0.7.0.dist-info/WHEEL
gosuslugi_api-0.7.0.dist-info/top_level.txt
gosuslugi_api-0.7.0.dist-info/RECORD
