Metadata-Version: 2.1
Name: gosuslugi-api
Version: 0.7.0
Summary: Toolset to work with dom.gosuslugi.ru API
Home-page: https://github.com/GregEremeev/gosuslugi-api
Author: Greg Eremeev
Author-email: gregory.eremeev@gmail.com
License: BSD-3-Clause
Platform: UNKNOWN
Classifier: Intended Audience :: Developers
Classifier: License :: OSI Approved :: BSD License
Classifier: Programming Language :: Python :: 3.7
Classifier: Programming Language :: Python :: Implementation :: CPython
Requires-Dist: requests (==2.25.1)
Requires-Dist: openpyxl (==3.0.7)
Provides-Extra: dev
Requires-Dist: ipdb (==0.12.2) ; extra == 'dev'
Requires-Dist: pytest (==5.2.1) ; extra == 'dev'
